pyoctopus/__init__.py
pyoctopus/limiter.py
pyoctopus/octopus.py
pyoctopus/request.py
pyoctopus/response.py
pyoctopus/site.py
pyoctopus/types.py
pyoctopus/collector/__init__.py
pyoctopus/collector/excel_collector.py
pyoctopus/collector/logging_collector.py
pyoctopus/converter/__init__.py
pyoctopus/converter/converter.py
pyoctopus/downloader/__init__.py
pyoctopus/downloader/downloader.py
pyoctopus/matcher/__init__.py
pyoctopus/matcher/matcher.py
pyoctopus/processor/__init__.py
pyoctopus/processor/downloader.py
pyoctopus/processor/extractor.py
pyoctopus/processor/processor.py
pyoctopus/selector/__init__.py
pyoctopus/selector/attr.py
pyoctopus/selector/css.py
pyoctopus/selector/header.py
pyoctopus/selector/id.py
pyoctopus/selector/json.py
pyoctopus/selector/query.py
pyoctopus/selector/regex.py
pyoctopus/selector/selector.py
pyoctopus/selector/url.py
pyoctopus/selector/xpath.py
pyoctopus/store/__init__.py
pyoctopus/store/memory_store.py
pyoctopus/store/redis_store.py
pyoctopus/store/sqlite_store.py
pyoctopus/store/store.py
tests/__init__.py
pyoctopus-0.2.3.dist-info/LICENSE
pyoctopus-0.2.3.dist-info/METADATA
pyoctopus-0.2.3.dist-info/WHEEL
pyoctopus-0.2.3.dist-info/top_level.txt
pyoctopus-0.2.3.dist-info/RECORD
