Metadata-Version: 2.1
Name: pyoctopus
Version: 0.2.3
Summary: A simple Python library for web crawler
Home-page: https://github.com/yangsholai/pyoctopus
Author: yangshoulai
Author-email: shoulai.yang@gmail.com
Classifier: Programming Language :: Python :: 3
Classifier: License :: OSI Approved :: MIT License
Classifier: Operating System :: OS Independent
Requires-Python: >=3.11
License-File: LICENSE
Requires-Dist: Requests
Requires-Dist: curl_cffi
Requires-Dist: beautifulsoup4
Requires-Dist: jsonpath_ng
Requires-Dist: lxml
Requires-Dist: tornado
Requires-Dist: redis
Requires-Dist: openpyxl
